[
  {
    "source": "edit few values",
    "steps": [
      {
        "name": "edit few values",
        "aggregatedDurations": {
          "average": 0.1105648,
          "median": 0.1105648
        },
        "durations": [
          {
            "duration": 0.1105648,
            "location": "file:Features/MatRevision.feature:32"
          }
        ]
      }
    ]
  },
  {
    "source": "click on submit button on edit materials page",
    "steps": [
      {
        "name": "click on submit button on edit materials page",
        "aggregatedDurations": {
          "average": 0.0238471,
          "median": 0.0238471
        },
        "durations": [
          {
            "duration": 0.0293962,
            "location": "file:Features/MatRevision.feature:33"
          },
          {
            "duration": 0.018298,
            "location": "file:Features/MatRevision.feature:37"
          }
        ]
      }
    ]
  },
  {
    "source": "click on first revision",
    "steps": [
      {
        "name": "click on first revision",
        "aggregatedDurations": {
          "average": 0.4581388,
          "median": 0.4581388
        },
        "durations": [
          {
            "duration": 0.4581388,
            "location": "file:Features/MatRevision.feature:39"
          }
        ]
      }
    ]
  },
  {
    "source": "user comes on Navigate WS",
    "steps": [
      {
        "name": "user comes on Navigate WS",
        "aggregatedDurations": {
          "average": 0.450133,
          "median": 0.450133
        },
        "durations": [
          {
            "duration": 0.450133,
            "location": "file:Features/MatRevision.feature:27"
          }
        ]
      }
    ]
  },
  {
    "source": "click on Edit material option",
    "steps": [
      {
        "name": "click on Edit material option",
        "aggregatedDurations": {
          "average": 2.54846245,
          "median": 2.54846245
        },
        "durations": [
          {
            "duration": 0.1963237,
            "location": "file:Features/MatRevision.feature:30"
          },
          {
            "duration": 4.9006012,
            "location": "file:Features/MatRevision.feature:34"
          }
        ]
      }
    ]
  },
  {
    "source": "homepage is displayed",
    "steps": [
      {
        "name": "homepage is displayed",
        "aggregatedDurations": {
          "average": 0.2353383,
          "median": 0.2353383
        },
        "durations": [
          {
            "duration": 0.2353383,
            "location": "file:Features/MatRevision.feature:7"
          }
        ]
      }
    ]
  },
  {
    "source": "double click on material",
    "steps": [
      {
        "name": "double click on material",
        "aggregatedDurations": {
          "average": 1.3765916,
          "median": 1.3765916
        },
        "durations": [
          {
            "duration": 1.3765916,
            "location": "file:Features/MatRevision.feature:29"
          }
        ]
      }
    ]
  },
  {
    "source": "navigate to Classification tab",
    "steps": [
      {
        "name": "navigate to Classification tab",
        "aggregatedDurations": {
          "average": 2.01203295,
          "median": 2.01203295
        },
        "durations": [
          {
            "duration": 2.6722034,
            "location": "file:Features/MatRevision.feature:31"
          },
          {
            "duration": 1.3518625,
            "location": "file:Features/MatRevision.feature:35"
          }
        ]
      }
    ]
  },
  {
    "source": "click on revisions tab",
    "steps": [
      {
        "name": "click on revisions tab",
        "aggregatedDurations": {
          "average": 3.7807442,
          "median": 3.7807442
        },
        "durations": [
          {
            "duration": 3.7807442,
            "location": "file:Features/MatRevision.feature:38"
          }
        ]
      }
    ]
  },
  {
    "source": "user clicks on Metals to open MOD",
    "steps": [
      {
        "name": "user clicks on Metals to open MOD",
        "aggregatedDurations": {
          "average": 0.7905005,
          "median": 0.7905005
        },
        "durations": [
          {
            "duration": 0.7905005,
            "location": "file:Features/MatRevision.feature:28"
          }
        ]
      }
    ]
  },
  {
    "source": "user has already logged in to Material Center application",
    "steps": [
      {
        "name": "user has already logged in to Material Center application",
        "aggregatedDurations": {
          "average": 8.736718,
          "median": 8.736718
        },
        "durations": [
          {
            "duration": 8.736718,
            "location": "file:Features/MatRevision.feature:4"
          }
        ]
      }
    ]
  },
  {
    "source": "edit subclass value",
    "steps": [
      {
        "name": "edit subclass value",
        "aggregatedDurations": {
          "average": 0.1010543,
          "median": 0.1010543
        },
        "durations": [
          {
            "duration": 0.1010543,
            "location": "file:Features/MatRevision.feature:36"
          }
        ]
      }
    ]
  },
  {
    "source": "verify that all differences are displayed in highlighted color",
    "steps": [
      {
        "name": "verify that all differences are displayed in highlighted color",
        "aggregatedDurations": {
          "average": 19.4186478,
          "median": 19.4186478
        },
        "durations": [
          {
            "duration": 19.4186478,
            "location": "file:Features/MatRevision.feature:40"
          }
        ]
      }
    ]
  }
]